movia/__init__.py
movia/__main__.py
movia/utils.py
movia/core/__init__.py
movia/core/exceptions.py
movia/core/analysis/__init__.py
movia/core/analysis/streams.py
movia/core/analysis/video/__init__.py
movia/core/analysis/video/properties/__init__.py
movia/core/analysis/video/properties/duration.py
movia/core/analysis/video/properties/framerate.py
movia/core/analysis/video/properties/nb_frames.py
movia/core/analysis/video/properties/parser.py
movia/core/analysis/video/properties/timestamps.py
movia/core/classes/__init__.py
movia/core/classes/container.py
movia/core/classes/filter.py
movia/core/classes/node.py
movia/core/classes/stream.py
movia/core/classes/stream_audio.py
movia/core/classes/stream_video.py
movia/core/compilation/__init__.py
movia/core/compilation/graph_to_ast.py
movia/core/compilation/graph_to_tree.py
movia/core/compilation/tree_to_graph.py
movia/core/compilation/export/__init__.py
movia/core/compilation/export/compatibility.py
movia/core/compilation/export/default.py
movia/core/compilation/export/encodec.py
movia/core/compilation/export/muxer.py
movia/core/compilation/export/rate_audio.py
movia/core/compilation/export/rate_video.py
movia/core/edit/__init__.py
movia/core/edit/operation/__init__.py
movia/core/edit/operation/add.py
movia/core/edit/operation/remove.py
movia/core/filters/__init__.py
movia/core/filters/basic/__init__.py
movia/core/filters/basic/truncate.py
movia/core/generation/__init__.py
movia/core/generation/audio/__init__.py
movia/core/generation/audio/empty.py
movia/core/generation/audio/noise.py
movia/core/generation/video/__init__.py
movia/core/generation/video/empty.py
movia/core/generation/video/equation.py
movia/core/generation/video/noise.py
movia/core/io/__init__.py
movia/core/io/read.py
movia/core/io/write.py
movia/gui/__init__.py
movia/gui/actions.py
movia/gui/base.py
movia/gui/edition_tabs.py
movia/gui/entry_tabs.py
movia/gui/main.py
movia/gui/menu.py
movia/gui/toolbar.py
movia/gui/video_viewer.py
movia/gui/app/__init__.py
movia-1.0a1.dist-info/LICENSE
movia-1.0a1.dist-info/METADATA
movia-1.0a1.dist-info/WHEEL
movia-1.0a1.dist-info/entry_points.txt
movia-1.0a1.dist-info/top_level.txt
movia-1.0a1.dist-info/RECORD
