Metadata-Version: 2.1
Name: movia
Version: 1.0a1
Summary: video editing softwear
Home-page: https://framagit.org/robinechuca/movia/-/blob/main/README.md
Author: Robin RICHARD (robinechuca)
Author-email: serveurpython.oz@gmail.com
Project-URL: Source Repository, https://framagit.org/robinechuca/movia/
Keywords: video,editing,ffmpeg,graphical
Classifier: Development Status :: 2 - Pre-Alpha
Classifier: Environment :: X11 Applications :: Qt
Classifier: Intended Audience :: Customer Service
Classifier: License :: OSI Approved :: GNU Affero General Public License v3 or later (AGPLv3+)
Classifier: Natural Language :: English
Classifier: Operating System :: POSIX :: Linux
Classifier: Programming Language :: Python :: 3
Classifier: Topic :: Multimedia
Classifier: Topic :: Multimedia :: Graphics :: Capture
Classifier: Topic :: Multimedia :: Graphics :: Editors
Classifier: Topic :: Multimedia :: Graphics :: Graphics Conversion
Classifier: Topic :: Multimedia :: Sound/Audio
Classifier: Topic :: Multimedia :: Sound/Audio :: Analysis
Classifier: Topic :: Multimedia :: Sound/Audio :: Conversion
Classifier: Topic :: Multimedia :: Sound/Audio :: Mixers
Classifier: Topic :: Multimedia :: Sound/Audio :: Players
Classifier: Topic :: Multimedia :: Video
Classifier: Topic :: Multimedia :: Video :: Capture
Classifier: Topic :: Multimedia :: Video :: Conversion
Classifier: Topic :: Multimedia :: Video :: Display
Classifier: Topic :: Multimedia :: Video :: Non-Linear Editor
Classifier: Topic :: Scientific/Engineering :: Image Processing
Requires-Python: >=3.9,<3.12
License-File: LICENSE
Requires-Dist: av
Requires-Dist: black
Requires-Dist: click
Requires-Dist: networkx
Requires-Dist: numpy (>=1.22)
Requires-Dist: opencv-contrib-python-headless
Requires-Dist: pdoc3
Requires-Dist: pygraphviz
Requires-Dist: pyqt6
Requires-Dist: sympy
Requires-Dist: unidecode
Provides-Extra: dev
Requires-Dist: pylint ; extra == 'dev'
Requires-Dist: pytest ; extra == 'dev'
